idmd/__init__.py
idmd/app.py
idmd/data/__init__.py
idmd/data/exporter.py
idmd/data/generator.py
idmd/data/uploader.py
idmd/manipulation/__init__.py
idmd/manipulation/columns.py
idmd/manipulation/replace.py
idmd/report/__init__.py
idmd/report/report.py
idmd/ui/__init__.py
idmd/ui/base.py
idmd/ui/columns_ui.py
idmd/ui/data_preview.py
idmd/ui/data_stats.py
idmd/ui/exporter_ui.py
idmd/ui/generator_ui.py
idmd/ui/replace_ui.py
idmd/ui/report_ui.py
idmd/ui/uploader_generator_ui.py
idmd/ui/uploader_ui.py
idmd/ui/visualizer_ui.py
idmd/visualization/__init__.py
idmd/visualization/heatmaps.py
idmd/visualization/histograms.py
idmd/visualization/plots.py
idmd/visualization/visualizer.py
idmd-0.0.2.dist-info/licenses/LICENSE
idmd-0.0.2.dist-info/METADATA
idmd-0.0.2.dist-info/WHEEL
idmd-0.0.2.dist-info/top_level.txt
idmd-0.0.2.dist-info/RECORD
