Metadata-Version: 2.4
Name: idmd
Version: 0.0.2
Summary: IDMD - Interactive Data Manipulator and Descriptor
Author: Bence Gercuj, Csongor Loránd Laczkó, Richárd Bence Rózsa
Maintainer-email: Bence Gercuj <gercuj.bence@hallgato.ppke.hu>, Csongor Loránd Laczkó <laczko.csongor.lorand@hallgato.ppke.hu>, Richárd Bence Rózsa <rozsa.richard.bence@hallgato.ppke.hu>
License-Expression: GPL-3.0-only
Project-URL: Homepage, https://github.com/CsongorLaczko/idmd
Project-URL: Documentation, https://idmd.readthedocs.io
Project-URL: Repository, https://github.com/CsongorLaczko/idmd.git
Project-URL: Issues, https://github.com/CsongorLaczko/idmd/issues
Classifier: Development Status :: 1 - Planning
Classifier: Programming Language :: Python :: 3.10
Classifier: Operating System :: OS Independent
Requires-Python: >=3.10
License-File: LICENSE
Requires-Dist: matplotlib==3.10.3
Requires-Dist: openpyxl==3.1.5
Requires-Dist: pandas==2.2.3
Requires-Dist: seaborn==0.13.2
Requires-Dist: streamlit==1.45.0
Dynamic: license-file
